Workbook

Sheet Lectura
B1: Orbit Rides — Modelo financiero (unit economics y sensibilidad de planes)
B2: Versión 0.1 · 27/07/2026 · construido sobre los supuestos de la hoja "Supuestos"
B4: Cómo usar este modelo
B5: Editá SOLO las celdas en AZUL de la hoja "Supuestos". Todo lo demás son fórmulas y se recalcula solo.
B6: Las celdas con FONDO AMARILLO son los supuestos que más mueven el resultado y los que debés verificar primero.
B8: Hojas
B9: Supuestos — todos los inputs: tarifa, volumen, planes, costos de procesamiento, costos fijos.
B10: BreakEven_Conductor — a partir de qué facturación le conviene a un conductor pagar Pro o Plus.
B11: Unit_Economics — cuánto te deja al mes un conductor de cada plan, y de dónde sale la plata.
B12: PL_Plataforma — proyección de 12 meses con crecimiento de conductores y mix de planes.
B13: Sensibilidad — grilla precio Pro × comisión Pro. Acá está la conclusión del modelo.
B15: La conclusión, corta
... B28: (4) tipo de cambio. Los cuatro cambian el resultado de forma material.
B31: Resultado con los supuestos actuales (se actualiza solo) | C31: Valor | D31: Qué significa
B32: Margen por conductor FREE (UYU/mes) | C32: =Unit_Economics!C21 -> 4797 | D32: Tu plan sin cuota.
B33: Margen por conductor PRO (UYU/mes) | C33: =Unit_Economics!D21 -> 1199 | D33: Con cuota US$ 70 y comisión 2%.
B34: Margen por conductor PLUS (UYU/mes) | C34: =Unit_Economics!E21 -> 3027 | D34: Con cuota US$ 150 y comisión 0%.
B35: Diferencia Pro vs Free | C35: =Unit_Economics!D21-Unit_Economics!C21 -> -3598 | D35: NEGATIVO = un conductor Pro te deja MENOS que el mismo conductor en Free.
B36: Resultado de un viaje Pro con tarjeta (UYU) | C36: =Unit_Economics!C31 -> -15.25 | D36: Sin contar la suscripción. Negativo = perdés en cada viaje.
B37: Comisión mínima — viaje promedio (mix de pagos) | C37: =Sensibilidad!C19 -> 0.043857143 | D37: Umbral del P&L mensual. Pondera el procesamiento por el % de tarjeta.
B38: Facturación desde la que Pro le conviene al conductor | C38: =BreakEven_Conductor!E6 -> 700 | D38: En USD/mes. Comparar con lo que factura un conductor real.
B39: Facturación desde la que Plus le conviene | C39: =BreakEven_Conductor!E7 -> 4000 | D39: Si supera lo que factura un full-time, ese plan no tiene mercado.
B40: Comisión mínima — viaje con tarjeta (estricto) | C40: =Sensibilidad!C21 -> 0.063571429 | D40: Si un conductor cobra todo con tarjeta, por debajo de esto pierde plata en cada viaje.
B41: Lo que dice este bloque, en una frase:
B42: Con los supuestos de partida, el plan FREE al 12% es tu cliente MÁS rentable, y cada escalón de
B43: suscripción destruye margen en lugar de crearlo. No es que el precio esté bajo: es que la comisión
B44: del 2% no alcanza a cubrir el costo de procesar el pago. Arreglás esto subiendo la comisión Pro
B45: a ~5% (ver la grilla de Sensibilidad) o agregando un fee de servicio al pasajero (Supuestos!C11).

Sheet Supuestos
B1: Supuestos
B2: Celdas azules = editables. Fondo amarillo = verificar antes de decidir precios.
B4: Macro | E4: Fuente / nota
B5: Tipo de cambio (UYU por USD) | C5: 40 | E5: ESTIMACIÓN. Verificar cotización BCU del día.
B7: Demanda y tarifa | E7: Fuente / nota
B8: Tarifa promedio por viaje (UYU) | C8: 350 | E8: ESTIMACIÓN de viaje urbano en Montevideo. Verificar con datos reales.
B9: Viajes por conductor activo por mes | C9: 180 | E9: ESTIMACIÓN: ~6 viajes/día × 30 días. Verificar en entrevistas a conductores.
B10: % de viajes pagados con tarjeta | C10: 0.6 | E10: ESTIMACIÓN. En Uruguay el efectivo sigue siendo fuerte; medir en piloto.
B11: Fee de servicio al pasajero (UYU/viaje) | C11: 0 | E11: DECISIÓN TUYA. Hoy en 0. Poner 20-30 cambia todo el modelo (probalo).
B13: Costos de procesamiento de pagos | E13: Fuente / nota
B14: Tarjeta: % sobre el monto | C14: 0.035 | E14: ESTIMACIÓN MercadoPago Uruguay. VERIFICAR: mueve todo el resultado.
B15: Tarjeta: costo fijo por transacción (UYU) | C15: 5 | E15: ESTIMACIÓN. Verificar con MercadoPago.
B16: Suscripción: % sobre el monto | C16: 0.035 | E16: ESTIMACIÓN de cobro recurrente. Verificar.
B18: Costos variables por viaje | E18: Fuente / nota
B19: Mapas y ruteo (UYU/viaje) | C19: 2 | E19: ESTIMACIÓN Mapbox. Escala con intentos de dispatch, no con viajes: puede ser más.
B20: Soporte y operaciones (UYU/viaje) | C20: 3 | E20: ESTIMACIÓN. Sube mucho si el % de incidencias es alto.
B22: Planes de conductor | E22: Fuente / nota
B23: Plan | C23: Cuota (USD/mes) | D23: Comisión | E23: Nota
B24: Free | C24: 0 | D24: 0.12 | E24: Tu propuesta. 12% ya es menos de la mitad de Uber (~25%).
B25: Pro | C25: 70 | D25: 0.02 | E25: Tu propuesta. Ver hoja Sensibilidad: al 2% con tarjeta da margen negativo.
B26: Plus | C26: 150 | D26: 0 | E26: Tu propuesta (comisión no estaba definida; asumo 0%). Sin mercado local hoy.
B28: Mix de conductores por plan (debe sumar 100%) | E28: Fuente / nota
B29: % en Free | C29: 0.7 | E29: ESTIMACIÓN. Ojo con la selección adversa: los de alto volumen migran a Pro.
B30: % en Pro | C30: 0.28 | E30: ESTIMACIÓN.
B31: % en Plus | C31: 0.02 | E31: ESTIMACIÓN.
B32: Control: suma del mix | C32: =C29+C30+C31 -> 1 | E32: Tiene que dar 100,0%.
B34: Crecimiento y costos fijos | E34: Fuente / nota
B35: Conductores activos en el mes 1 | C35: 10 | E35: Plan de lanzamiento: reclutados a mano.
B36: Crecimiento mensual de conductores | C36: 0.25 | E36: ESTIMACIÓN agresiva. 25%/mes sostenido es difícil.
B37: Infraestructura (USD/mes) | C37: 400 | E37: Contenedores + Postgres + Redis administrados.
B38: Equipo (USD/mes) | C38: 6000 | E38: ESTIMACIÓN: 2-3 devs. El costo dominante. Ajustar a tu realidad.
B39: Legal y contable (USD/mes) | C39: 800 | E39: Regulatorio, URCDP, DGI, seguros.
B40: Marketing y adquisición (USD/mes) | C40: 2000 | E40: ESTIMACIÓN. Incentivos de arranque en frío pueden ser mucho más.
B41: Total costos fijos (USD/mes) | C41: =SUM(C37:C40) -> 9200
B42: Total costos fijos (UYU/mes) | C42: =C41*C5 -> 368000

Sheet BreakEven_Conductor
B1: ¿Desde qué facturación le conviene al conductor pagar?
B2: Ingreso NETO del conductor (después de comisión y de la cuota del plan), en UYU/mes.
B4: Punto de indiferencia entre planes | E4: Fuente / nota
B5: Concepto | C5: Facturación bruta (UYU/mes) | D5: Equivale a (viajes/mes) | E5: En USD/mes
B6: Free → Pro le conviene desde | C6: =IFERROR(Supuestos!C25*Supuestos!C5/(Supuestos!D24-Supuestos!D25),"n/a") -> 28000 | D6: =IFERROR(C6/Supuestos!C8,"n/a") -> 80 | E6: =IFERROR(C6/Supuestos!C5,"n/a") -> 700
B7: Pro → Plus le conviene desde | C7: =IFERROR((Supuestos!C26-Supuestos!C25)*Supuestos!C5/(Supuestos!D25-Supuestos!D26),"n/a") -> 160000 | D7: =IFERROR(C7/Supuestos!C8,"n/a") -> 457.14286 | E7: =IFERROR(C7/Supuestos!C5,"n/a") -> 4000
B8: Free → Plus le conviene desde | C8: =IFERROR(Supuestos!C26*Supuestos!C5/(Supuestos!D24-Supuestos!D26),"n/a") -> 50000 | D8: =IFERROR(C8/Supuestos!C8,"n/a") -> 142.85714 | E8: =IFERROR(C8/Supuestos!C5,"n/a") -> 1250
B9: Referencia: facturación de un conductor con los supuestos actuales | C9: =Supuestos!C8*Supuestos!C9 -> 63000 | D9: =Supuestos!C9 -> 180 | E9: =C9/Supuestos!C5 -> 1575
I10: Si el punto de indiferencia está MUY por encima de la fila 9, ese plan no tiene mercado.
B12: Ingreso neto del conductor según facturación y plan (UYU/mes) | E12: Fuente / nota
B13: Facturación bruta (UYU/mes) | C13: Viajes/mes equiv. | D13: Neto en Free | E13: Neto en Pro | F13: Neto en Plus | G13: Mejor plan | H13: Ventaja del mejor vs Free
B14: 10000 | C14: =B14/Supuestos!C8 -> 28.571429 | D14: =B14*(1-Supuestos!$D$24)-Supuestos!$C$24*Supuestos!$C$5 -> 8800 | E14: =B14*(1-Supuestos!$D$25)-Supuestos!$C$25*Supuestos!$C$5 -> 7000 | F14: =B14*(1-Supuestos!$D$26)-Supuestos!$C$26*Supuestos!$C$5 -> 4000 | G14: =IF(D14>=MAX(D14:F14),"Free",IF(E14>=MAX(D14:F14),"Pro","Plus")) -> Free | H14: =MAX(D14:F14)-D14 -> 0
B15: 15000 | C15: =B15/Supuestos!C8 -> 42.857143 | D15: =B15*(1-Supuestos!$D$24)-Supuestos!$C$24*Supuestos!$C$5 -> 13200 | E15: =B15*(1-Supuestos!$D$25)-Supuestos!$C$25*Supuestos!$C$5 -> 11900 | F15: =B15*(1-Supuestos!$D$26)-Supuestos!$C$26*Supuestos!$C$5 -> 9000 | G15: =IF(D15>=MAX(D15:F15),"Free",IF(E15>=MAX(D15:F15),"Pro","Plus")) -> Free | H15: =MAX(D15:F15)-D15 -> 0
B16: 20000 | C16: =B16/Supuestos!C8 -> 57.142857 | D16: =B16*(1-Supuestos!$D$24)-Supuestos!$C$24*Supuestos!$C$5 -> 17600 | E16: =B16*(1-Supuestos!$D$25)-Supuestos!$C$25*Supuestos!$C$5 -> 16800 | F16: =B16*(1-Supuestos!$D$26)-Supuestos!$C$26*Supuestos!$C$5 -> 14000 | G16: =IF(D16>=MAX(D16:F16),"Free",IF(E16>=MAX(D16:F16),"Pro","Plus")) -> Free | H16: =MAX(D16:F16)-D16 -> 0
B17: 25000 | C17: =B17/Supuestos!C8 -> 71.428571 | D17: =B17*(1-Supuestos!$D$24)-Supuestos!$C$24*Supuestos!$C$5 -> 22000 | E17: =B17*(1-Supuestos!$D$25)-Supuestos!$C$25*Supuestos!$C$5 -> 21700 | F17: =B17*(1-Supuestos!$D$26)-Supuestos!$C$26*Supuestos!$C$5 -> 19000 | G17: =IF(D17>=MAX(D17:F17),"Free",IF(E17>=MAX(D17:F17),"Pro","Plus")) -> Free | H17: =MAX(D17:F17)-D17 -> 0
B18: 30000 | C18: =B18/Supuestos!C8 -> 85.714286 | D18: =B18*(1-Supuestos!$D$24)-Supuestos!$C$24*Supuestos!$C$5 -> 26400 | E18: =B18*(1-Supuestos!$D$25)-Supuestos!$C$25*Supuestos!$C$5 -> 26600 | F18: =B18*(1-Supuestos!$D$26)-Supuestos!$C$26*Supuestos!$C$5 -> 24000 | G18: =IF(D18>=MAX(D18:F18),"Free",IF(E18>=MAX(D18:F18),"Pro","Plus")) -> Pro | H18: =MAX(D18:F18)-D18 -> 200
B19: 35000 | C19: =B19/Supuestos!C8 -> 100 | D19: =B19*(1-Supuestos!$D$24)-Supuestos!$C$24*Supuestos!$C$5 -> 30800 | E19: =B19*(1-Supuestos!$D$25)-Supuestos!$C$25*Supuestos!$C$5 -> 31500 | F19: =B19*(1-Supuestos!$D$26)-Supuestos!$C$26*Supuestos!$C$5 -> 29000 | G19: =IF(D19>=MAX(D19:F19),"Free",IF(E19>=MAX(D19:F19),"Pro","Plus")) -> Pro | H19: =MAX(D19:F19)-D19 -> 700
B20: 40000 | C20: =B20/Supuestos!C8 -> 114.28571 | D20: =B20*(1-Supuestos!$D$24)-Supuestos!$C$24*Supuestos!$C$5 -> 35200 | E20: =B20*(1-Supuestos!$D$25)-Supuestos!$C$25*Supuestos!$C$5 -> 36400 | F20: =B20*(1-Supuestos!$D$26)-Supuestos!$C$26*Supuestos!$C$5 -> 34000 | G20: =IF(D20>=MAX(D20:F20),"Free",IF(E20>=MAX(D20:F20),"Pro","Plus")) -> Pro | H20: =MAX(D20:F20)-D20 -> 1200
B21: 45000 | C21: =B21/Supuestos!C8 -> 128.57143 | D21: =B21*(1-Supuestos!$D$24)-Supuestos!$C$24*Supuestos!$C$5 -> 39600 | E21: =B21*(1-Supuestos!$D$25)-Supuestos!$C$25*Supuestos!$C$5 -> 41300 | F21: =B21*(1-Supuestos!$D$26)-Supuestos!$C$26*Supuestos!$C$5 -> 39000 | G21: =IF(D21>=MAX(D21:F21),"Free",IF(E21>=MAX(D21:F21),"Pro","Plus")) -> Pro | H21: =MAX(D21:F21)-D21 -> 1700
B22: 50000 | C22: =B22/Supuestos!C8 -> 142.85714 | D22: =B22*(1-Supuestos!$D$24)-Supuestos!$C$24*Supuestos!$C$5 -> 44000 | E22: =B22*(1-Supuestos!$D$25)-Supuestos!$C$25*Supuestos!$C$5 -> 46200 | F22: =B22*(1-Supuestos!$D$26)-Supuestos!$C$26*Supuestos!$C$5 -> 44000 | G22: =IF(D22>=MAX(D22:F22),"Free",IF(E22>=MAX(D22:F22),"Pro","Plus")) -> Pro | H22: =MAX(D22:F22)-D22 -> 2200
B23: 55000 | C23: =B23/Supuestos!C8 -> 157.14286 | D23: =B23*(1-Supuestos!$D$24)-Supuestos!$C$24*Supuestos!$C$5 -> 48400 | E23: =B23*(1-Supuestos!$D$25)-Supuestos!$C$25*Supuestos!$C$5 -> 51100 | F23: =B23*(1-Supuestos!$D$26)-Supuestos!$C$26*Supuestos!$C$5 -> 49000 | G23: =IF(D23>=MAX(D23:F23),"Free",IF(E23>=MAX(D23:F23),"Pro","Plus")) -> Pro | H23: =MAX(D23:F23)-D23 -> 2700
B24: 60000 | C24: =B24/Supuestos!C8 -> 171.42857 | D24: =B24*(1-Supuestos!$D$24)-Supuestos!$C$24*Supuestos!$C$5 -> 52800 | E24: =B24*(1-Supuestos!$D$25)-Supuestos!$C$25*Supuestos!$C$5 -> 56000 | F24: =B24*(1-Supuestos!$D$26)-Supuestos!$C$26*Supuestos!$C$5 -> 54000 | G24: =IF(D24>=MAX(D24:F24),"Free",IF(E24>=MAX(D24:F24),"Pro","Plus")) -> Pro | H24: =MAX(D24:F24)-D24 -> 3200
B25: 65000 | C25: =B25/Supuestos!C8 -> 185.71429 | D25: =B25*(1-Supuestos!$D$24)-Supuestos!$C$24*Supuestos!$C$5 -> 57200 | E25: =B25*(1-Supuestos!$D$25)-Supuestos!$C$25*Supuestos!$C$5 -> 60900 | F25: =B25*(1-Supuestos!$D$26)-Supuestos!$C$26*Supuestos!$C$5 -> 59000 | G25: =IF(D25>=MAX(D25:F25),"Free",IF(E25>=MAX(D25:F25),"Pro","Plus")) -> Pro | H25: =MAX(D25:F25)-D25 -> 3700
B26: 70000 | C26: =B26/Supuestos!C8 -> 200 | D26: =B26*(1-Supuestos!$D$24)-Supuestos!$C$24*Supuestos!$C$5 -> 61600 | E26: =B26*(1-Supuestos!$D$25)-Supuestos!$C$25*Supuestos!$C$5 -> 65800 | F26: =B26*(1-Supuestos!$D$26)-Supuestos!$C$26*Supuestos!$C$5 -> 64000 | G26: =IF(D26>=MAX(D26:F26),"Free",IF(E26>=MAX(D26:F26),"Pro","Plus")) -> Pro | H26: =MAX(D26:F26)-D26 -> 4200
B27: 75000 | C27: =B27/Supuestos!C8 -> 214.28571 | D27: =B27*(1-Supuestos!$D$24)-Supuestos!$C$24*Supuestos!$C$5 -> 66000 | E27: =B27*(1-Supuestos!$D$25)-Supuestos!$C$25*Supuestos!$C$5 -> 70700 | F27: =B27*(1-Supuestos!$D$26)-Supuestos!$C$26*Supuestos!$C$5 -> 69000 | G27: =IF(D27>=MAX(D27:F27),"Free",IF(E27>=MAX(D27:F27),"Pro","Plus")) -> Pro | H27: =MAX(D27:F27)-D27 -> 4700
B28: 80000 | C28: =B28/Supuestos!C8 -> 228.57143 | D28: =B28*(1-Supuestos!$D$24)-Supuestos!$C$24*Supuestos!$C$5 -> 70400 | E28: =B28*(1-Supuestos!$D$25)-Supuestos!$C$25*Supuestos!$C$5 -> 75600 | F28: =B28*(1-Supuestos!$D$26)-Supuestos!$C$26*Supuestos!$C$5 -> 74000 | G28: =IF(D28>=MAX(D28:F28),"Free",IF(E28>=MAX(D28:F28),"Pro","Plus")) -> Pro | H28: =MAX(D28:F28)-D28 -> 5200
B29: 85000 | C29: =B29/Supuestos!C8 -> 242.85714 | D29: =B29*(1-Supuestos!$D$24)-Supuestos!$C$24*Supuestos!$C$5 -> 74800 | E29: =B29*(1-Supuestos!$D$25)-Supuestos!$C$25*Supuestos!$C$5 -> 80500 | F29: =B29*(1-Supuestos!$D$26)-Supuestos!$C$26*Supuestos!$C$5 -> 79000 | G29: =IF(D29>=MAX(D29:F29),"Free",IF(E29>=MAX(D29:F29),"Pro","Plus")) -> Pro | H29: =MAX(D29:F29)-D29 -> 5700
B30: 90000 | C30: =B30/Supuestos!C8 -> 257.14286 | D30: =B30*(1-Supuestos!$D$24)-Supuestos!$C$24*Supuestos!$C$5 -> 79200 | E30: =B30*(1-Supuestos!$D$25)-Supuestos!$C$25*Supuestos!$C$5 -> 85400 | F30: =B30*(1-Supuestos!$D$26)-Supuestos!$C$26*Supuestos!$C$5 -> 84000 | G30: =IF(D30>=MAX(D30:F30),"Free",IF(E30>=MAX(D30:F30),"Pro","Plus")) -> Pro | H30: =MAX(D30:F30)-D30 -> 6200
B31: 95000 | C31: =B31/Supuestos!C8 -> 271.42857 | D31: =B31*(1-Supuestos!$D$24)-Supuestos!$C$24*Supuestos!$C$5 -> 83600 | E31: =B31*(1-Supuestos!$D$25)-Supuestos!$C$25*Supuestos!$C$5 -> 90300 | F31: =B31*(1-Supuestos!$D$26)-Supuestos!$C$26*Supuestos!$C$5 -> 89000 | G31: =IF(D31>=MAX(D31:F31),"Free",IF(E31>=MAX(D31:F31),"Pro","Plus")) -> Pro | H31: =MAX(D31:F31)-D31 -> 6700
B32: 100000 | C32: =B32/Supuestos!C8 -> 285.71429 | D32: =B32*(1-Supuestos!$D$24)-Supuestos!$C$24*Supuestos!$C$5 -> 88000 | E32: =B32*(1-Supuestos!$D$25)-Supuestos!$C$25*Supuestos!$C$5 -> 95200 | F32: =B32*(1-Supuestos!$D$26)-Supuestos!$C$26*Supuestos!$C$5 -> 94000 | G32: =IF(D32>=MAX(D32:F32),"Free",IF(E32>=MAX(D32:F32),"Pro","Plus")) -> Pro | H32: =MAX(D32:F32)-D32 -> 7200
B33: 105000 | C33: =B33/Supuestos!C8 -> 300 | D33: =B33*(1-Supuestos!$D$24)-Supuestos!$C$24*Supuestos!$C$5 -> 92400 | E33: =B33*(1-Supuestos!$D$25)-Supuestos!$C$25*Supuestos!$C$5 -> 100100 | F33: =B33*(1-Supuestos!$D$26)-Supuestos!$C$26*Supuestos!$C$5 -> 99000 | G33: =IF(D33>=MAX(D33:F33),"Free",IF(E33>=MAX(D33:F33),"Pro","Plus")) -> Pro | H33: =MAX(D33:F33)-D33 -> 7700
B34: 110000 | C34: =B34/Supuestos!C8 -> 314.28571 | D34: =B34*(1-Supuestos!$D$24)-Supuestos!$C$24*Supuestos!$C$5 -> 96800 | E34: =B34*(1-Supuestos!$D$25)-Supuestos!$C$25*Supuestos!$C$5 -> 105000 | F34: =B34*(1-Supuestos!$D$26)-Supuestos!$C$26*Supuestos!$C$5 -> 104000 | G34: =IF(D34>=MAX(D34:F34),"Free",IF(E34>=MAX(D34:F34),"Pro","Plus")) -> Pro | H34: =MAX(D34:F34)-D34 -> 8200
B35: 115000 | C35: =B35/Supuestos!C8 -> 328.57143 | D35: =B35*(1-Supuestos!$D$24)-Supuestos!$C$24*Supuestos!$C$5 -> 101200 | E35: =B35*(1-Supuestos!$D$25)-Supuestos!$C$25*Supuestos!$C$5 -> 109900 | F35: =B35*(1-Supuestos!$D$26)-Supuestos!$C$26*Supuestos!$C$5 -> 109000 | G35: =IF(D35>=MAX(D35:F35),"Free",IF(E35>=MAX(D35:F35),"Pro","Plus")) -> Pro | H35: =MAX(D35:F35)-D35 -> 8700
B36: 120000 | C36: =B36/Supuestos!C8 -> 342.85714 | D36: =B36*(1-Supuestos!$D$24)-Supuestos!$C$24*Supuestos!$C$5 -> 105600 | E36: =B36*(1-Supuestos!$D$25)-Supuestos!$C$25*Supuestos!$C$5 -> 114800 | F36: =B36*(1-Supuestos!$D$26)-Supuestos!$C$26*Supuestos!$C$5 -> 114000 | G36: =IF(D36>=MAX(D36:F36),"Free",IF(E36>=MAX(D36:F36),"Pro","Plus")) -> Pro | H36: =MAX(D36:F36)-D36 -> 9200
B37: 125000 | C37: =B37/Supuestos!C8 -> 357.14286 | D37: =B37*(1-Supuestos!$D$24)-Supuestos!$C$24*Supuestos!$C$5 -> 110000 | E37: =B37*(1-Supuestos!$D$25)-Supuestos!$C$25*Supuestos!$C$5 -> 119700 | F37: =B37*(1-Supuestos!$D$26)-Supuestos!$C$26*Supuestos!$C$5 -> 119000 | G37: =IF(D37>=MAX(D37:F37),"Free",IF(E37>=MAX(D37:F37),"Pro","Plus")) -> Pro | H37: =MAX(D37:F37)-D37 -> 9700
B39: La columna azul es editable: cambiá los niveles de facturación que quieras evaluar.

Sheet Unit_Economics
B1: ¿Cuánto te deja al mes un conductor de cada plan?
B2: Todo en UYU/mes, para UN conductor con los viajes/mes de la hoja Supuestos.
B4: Margen de contribución por conductor y por mes | E4: Fuente / nota
B5: Concepto | C5: Free | D5: Pro | E5: Plus | F5: Nota
B6: Viajes por mes | C6: =Supuestos!$C$9 -> 180 | D6: =Supuestos!$C$9 -> 180 | E6: =Supuestos!$C$9 -> 180
B7: Facturación bruta del conductor (GMV) | C7: =Supuestos!$C$9*Supuestos!$C$8 -> 63000 | D7: =Supuestos!$C$9*Supuestos!$C$8 -> 63000 | E7: =Supuestos!$C$9*Supuestos!$C$8 -> 63000 | F7: Esto NO es tu ingreso: es lo que paga el pasajero.
B9: INGRESOS
B10: Ingreso por comisión | C10: =C7*Supuestos!$D$24 -> 7560 | D10: =D7*Supuestos!$D$25 -> 1260 | E10: =E7*Supuestos!$D$26 -> 0 | F10: GMV × comisión del plan.
B11: Ingreso por fee de servicio | C11: =Supuestos!$C$9*Supuestos!$C$11 -> 0 | D11: =Supuestos!$C$9*Supuestos!$C$11 -> 0 | E11: =Supuestos!$C$9*Supuestos!$C$11 -> 0 | F11: Hoy 0. Es la palanca más limpia para cubrir el procesamiento.
B12: Ingreso por suscripción | C12: =Supuestos!$C$24*Supuestos!$C$5 -> 0 | D12: =Supuestos!$C$25*Supuestos!$C$5 -> 2800 | E12: =Supuestos!$C$26*Supuestos!$C$5 -> 6000 | F12: Cuota mensual convertida a UYU.
B13: Ingresos totales | C13: =SUM(C10:C12) -> 7560 | D13: =SUM(D10:D12) -> 4060 | E13: =SUM(E10:E12) -> 6000
B15: COSTOS
B16: Procesamiento de viajes con tarjeta | C16: =-(C7*Supuestos!$C$10*Supuestos!$C$14+Supuestos!$C$9*Supuestos!$C$10*Supuestos!$C$15) -> -1863 | D16: =-(D7*Supuestos!$C$10*Supuestos!$C$14+Supuestos!$C$9*Supuestos!$C$10*Supuestos!$C$15) -> -1863 | E16: =-(E7*Supuestos!$C$10*Supuestos!$C$14+Supuestos!$C$9*Supuestos!$C$10*Supuestos!$C$15) -> -1863 | F16: Se aplica sobre el GMV completo, no sobre tu comisión. Acá está el problema.
B17: Procesamiento de la suscripción | C17: =-C12*Supuestos!$C$16 -> 0 | D17: =-D12*Supuestos!$C$16 -> -98 | E17: =-E12*Supuestos!$C$16 -> -210
B18: Mapas, ruteo, soporte | C18: =-Supuestos!$C$9*(Supuestos!$C$19+Supuestos!$C$20) -> -900 | D18: =-Supuestos!$C$9*(Supuestos!$C$19+Supuestos!$C$20) -> -900 | E18: =-Supuestos!$C$9*(Supuestos!$C$19+Supuestos!$C$20) -> -900
B19: Costos totales | C19: =SUM(C16:C18) -> -2763 | D19: =SUM(D16:D18) -> -2861 | E19: =SUM(E16:E18) -> -2973
B21: MARGEN DE CONTRIBUCIÓN por conductor/mes | C21: =C13+C19 -> 4797 | D21: =D13+D19 -> 1199 | E21: =E13+E19 -> 3027 | F21: Si esto es negativo, cada conductor de ese plan te cuesta plata.
B22: Margen por viaje | C22: =C21/Supuestos!$C$9 -> 26.65 | D22: =D21/Supuestos!$C$9 -> 6.6611111 | E22: =E21/Supuestos!$C$9 -> 16.816667
B23: Take rate efectivo sobre GMV | C23: =IFERROR(C21/C7,0) -> 0.076142857 | D23: =IFERROR(D21/D7,0) -> 0.019031746 | E23: =IFERROR(E21/E7,0) -> 0.048047619 | F23: Lo que realmente te queda del dinero que mueve la plataforma.
B25: Prueba del problema: el viaje con tarjeta de un conductor Pro | E25: Fuente / nota
B26: Tarifa del viaje (UYU) | C26: =Supuestos!C8 -> 350
B27: Comisión que cobrás (plan Pro) | C27: =C26*Supuestos!D25 -> 7 | F27: Tu ingreso por ese viaje.
B28: Fee de servicio al pasajero | C28: =Supuestos!C11 -> 0 | F28: Hoy 0.
B29: Costo de procesar la tarjeta | C29: =-(C26*Supuestos!C14+Supuestos!C15) -> -17.25 | F29: Se cobra sobre la tarifa completa.
B30: Mapas, ruteo y soporte | C30: =-(Supuestos!C19+Supuestos!C20) -> -5
B31: RESULTADO del viaje (sin suscripción) | C31: =SUM(C27:C30) -> -15.25 | F31: Negativo = perdés plata en ESE viaje. Ojo: el margen mensual de la fila 21 ya pondera el mix de pagos.
B32: Viajes/mes que la suscripción alcanza a subsidiar | C32: =IFERROR(IF(C31>=0,"todos (no hace falta subsidio)",(Supuestos!C25*Supuestos!C5*(1-Supuestos!C16))/-C31),"n/a") -> 177.18033 | F32: Si este número es MENOR a los viajes/mes reales, el plan pierde dinero.
B33: Viajes/mes reales del supuesto | C33: =Supuestos!C9 -> 180

Sheet PL_Plataforma
B1: Proyección 12 meses (UYU)
B2: Crecimiento de conductores y mix de planes desde la hoja Supuestos. Escenario ilustrativo, no un pronóstico.
B4: Mes | C4: M1 | D4: M2 | E4: M3 | F4: M4 | G4: M5 | H4: M6 | I4: M7 | J4: M8 | K4: M9 | L4: M10 | M4: M11 | N4: M12
B5: Conductores activos | C5: =Supuestos!$C$35 -> 10 | D5: =ROUND(C5*(1+Supuestos!$C$36),0) -> 13 | E5: =ROUND(D5*(1+Supuestos!$C$36),0) -> 16 | F5: =ROUND(E5*(1+Supuestos!$C$36),0) -> 20 | G5: =ROUND(F5*(1+Supuestos!$C$36),0) -> 25 | H5: =ROUND(G5*(1+Supuestos!$C$36),0) -> 31 | I5: =ROUND(H5*(1+Supuestos!$C$36),0) -> 39 | J5: =ROUND(I5*(1+Supuestos!$C$36),0) -> 49 | K5: =ROUND(J5*(1+Supuestos!$C$36),0) -> 61 | ... N5: =ROUND(M5*(1+Supuestos!$C$36),0) -> 119
B6: en Free | C6: =C5*Supuestos!$C$29 -> 7 | D6: =D5*Supuestos!$C$29 -> 9.1 | E6: =E5*Supuestos!$C$29 -> 11.2 | F6: =F5*Supuestos!$C$29 -> 14 | G6: =G5*Supuestos!$C$29 -> 17.5 | H6: =H5*Supuestos!$C$29 -> 21.7 | I6: =I5*Supuestos!$C$29 -> 27.3 | J6: =J5*Supuestos!$C$29 -> 34.3 | ... N6: =N5*Supuestos!$C$29 -> 83.3
B7: en Pro | C7: =C5*Supuestos!$C$30 -> 2.8 | D7: =D5*Supuestos!$C$30 -> 3.64 | E7: =E5*Supuestos!$C$30 -> 4.48 | F7: =F5*Supuestos!$C$30 -> 5.6 | G7: =G5*Supuestos!$C$30 -> 7 | H7: =H5*Supuestos!$C$30 -> 8.68 | I7: =I5*Supuestos!$C$30 -> 10.92 | J7: =J5*Supuestos!$C$30 -> 13.72 | ... N7: =N5*Supuestos!$C$30 -> 33.32
B8: en Plus | C8: =C5*Supuestos!$C$31 -> 0.2 | D8: =D5*Supuestos!$C$31 -> 0.26 | E8: =E5*Supuestos!$C$31 -> 0.32 | F8: =F5*Supuestos!$C$31 -> 0.4 | G8: =G5*Supuestos!$C$31 -> 0.5 | H8: =H5*Supuestos!$C$31 -> 0.62 | I8: =I5*Supuestos!$C$31 -> 0.78 | J8: =J5*Supuestos!$C$31 -> 0.98 | ... N8: =N5*Supuestos!$C$31 -> 2.38
B9: Viajes totales | C9: =C5*Supuestos!$C$9 -> 1800 | D9: =D5*Supuestos!$C$9 -> 2340 | E9: =E5*Supuestos!$C$9 -> 2880 | F9: =F5*Supuestos!$C$9 -> 3600 | G9: =G5*Supuestos!$C$9 -> 4500 | H9: =H5*Supuestos!$C$9 -> 5580 | I9: =I5*Supuestos!$C$9 -> 7020 | J9: =J5*Supuestos!$C$9 -> 8820 | ... N9: =N5*Supuestos!$C$9 -> 21420
B10: GMV (lo que pagan los pasajeros) | C10: =C9*Supuestos!$C$8 -> 630000 | D10: =D9*Supuestos!$C$8 -> 819000 | E10: =E9*Supuestos!$C$8 -> 1008000 | F10: =F9*Supuestos!$C$8 -> 1260000 | G10: =G9*Supuestos!$C$8 -> 1575000 | H10: =H9*Supuestos!$C$8 -> 1953000 | I10: =I9*Supuestos!$C$8 -> 2457000 | J10: =J9*Supuestos!$C$8 -> 3087000 | ... N10: =N9*Supuestos!$C$8 -> 7497000
B12: Ingreso por comisión | C12: =Supuestos!$C$8*Supuestos!$C$9*(C6*Supuestos!$D$24+C7*Supuestos!$D$25+C8*Supuestos!$D$26) -> 56448 | D12: =Supuestos!$C$8*Supuestos!$C$9*(D6*Supuestos!$D$24+D7*Supuestos!$D$25+D8*Supuestos!$D$26) -> 73382.4 | E12: =Supuestos!$C$8*Supuestos!$C$9*(E6*Supuestos!$D$24+E7*Supuestos!$D$25+E8*Supuestos!$D$26) -> 90316.8 | F12: =Supuestos!$C$8*Supuestos!$C$9*(F6*Supuestos!$D$24+F7*Supuestos!$D$25+F8*Supuestos!$D$26) -> 112896 | G12: =Supuestos!$C$8*Supuestos!$C$9*(G6*Supuestos!$D$24+G7*Supuestos!$D$25+G8*Supuestos!$D$26) -> 141120 | H12: =Supuestos!$C$8*Supuestos!$C$9*(H6*Supuestos!$D$24+H7*Supuestos!$D$25+H8*Supuestos!$D$26) -> 174988.8 | I12: =Supuestos!$C$8*Supuestos!$C$9*(I6*Supuestos!$D$24+I7*Supuestos!$D$25+I8*Supuestos!$D$26) -> 220147.2 | J12: =Supuestos!$C$8*Supuestos!$C$9*(J6*Supuestos!$D$24+J7*Supuestos!$D$25+J8*Supuestos!$D$26) -> 276595.2 | ... N12: =Supuestos!$C$8*Supuestos!$C$9*(N6*Supuestos!$D$24+N7*Supuestos!$D$25+N8*Supuestos!$D$26) -> 671731.2
B13: Ingreso por suscripciones | C13: =(C7*Supuestos!$C$25+C8*Supuestos!$C$26)*Supuestos!$C$5 -> 9040 | D13: =(D7*Supuestos!$C$25+D8*Supuestos!$C$26)*Supuestos!$C$5 -> 11752 | E13: =(E7*Supuestos!$C$25+E8*Supuestos!$C$26)*Supuestos!$C$5 -> 14464 | F13: =(F7*Supuestos!$C$25+F8*Supuestos!$C$26)*Supuestos!$C$5 -> 18080 | G13: =(G7*Supuestos!$C$25+G8*Supuestos!$C$26)*Supuestos!$C$5 -> 22600 | H13: =(H7*Supuestos!$C$25+H8*Supuestos!$C$26)*Supuestos!$C$5 -> 28024 | I13: =(I7*Supuestos!$C$25+I8*Supuestos!$C$26)*Supuestos!$C$5 -> 35256 | J13: =(J7*Supuestos!$C$25+J8*Supuestos!$C$26)*Supuestos!$C$5 -> 44296 | ... N13: =(N7*Supuestos!$C$25+N8*Supuestos!$C$26)*Supuestos!$C$5 -> 107576
B14: Ingreso por fee de servicio | C14: =C9*Supuestos!$C$11 -> 0 | D14: =D9*Supuestos!$C$11 -> 0 | E14: =E9*Supuestos!$C$11 -> 0 | F14: =F9*Supuestos!$C$11 -> 0 | G14: =G9*Supuestos!$C$11 -> 0 | H14: =H9*Supuestos!$C$11 -> 0 | I14: =I9*Supuestos!$C$11 -> 0 | J14: =J9*Supuestos!$C$11 -> 0 | ... N14: =N9*Supuestos!$C$11 -> 0
B15: Ingresos totales | C15: =SUM(C12:C14) -> 65488 | D15: =SUM(D12:D14) -> 85134.4 | E15: =SUM(E12:E14) -> 104780.8 | F15: =SUM(F12:F14) -> 130976 | G15: =SUM(G12:G14) -> 163720 | H15: =SUM(H12:H14) -> 203012.8 | I15: =SUM(I12:I14) -> 255403.2 | J15: =SUM(J12:J14) -> 320891.2 | ... N15: =SUM(N12:N14) -> 779307.2
B17: Procesamiento de viajes | C17: =-(C10*Supuestos!$C$10*Supuestos!$C$14+C9*Supuestos!$C$10*Supuestos!$C$15) -> -18630 | D17: =-(D10*Supuestos!$C$10*Supuestos!$C$14+D9*Supuestos!$C$10*Supuestos!$C$15) -> -24219 | E17: =-(E10*Supuestos!$C$10*Supuestos!$C$14+E9*Supuestos!$C$10*Supuestos!$C$15) -> -29808 | F17: =-(F10*Supuestos!$C$10*Supuestos!$C$14+F9*Supuestos!$C$10*Supuestos!$C$15) -> -37260 | G17: =-(G10*Supuestos!$C$10*Supuestos!$C$14+G9*Supuestos!$C$10*Supuestos!$C$15) -> -46575 | H17: =-(H10*Supuestos!$C$10*Supuestos!$C$14+H9*Supuestos!$C$10*Supuestos!$C$15) -> -57753 | I17: =-(I10*Supuestos!$C$10*Supuestos!$C$14+I9*Supuestos!$C$10*Supuestos!$C$15) -> -72657 | J17: =-(J10*Supuestos!$C$10*Supuestos!$C$14+J9*Supuestos!$C$10*Supuestos!$C$15) -> -91287 | ... N17: =-(N10*Supuestos!$C$10*Supuestos!$C$14+N9*Supuestos!$C$10*Supuestos!$C$15) -> -221697
B18: Procesamiento de suscripciones | C18: =-C13*Supuestos!$C$16 -> -316.4 | D18: =-D13*Supuestos!$C$16 -> -411.32 | E18: =-E13*Supuestos!$C$16 -> -506.24 | F18: =-F13*Supuestos!$C$16 -> -632.8 | G18: =-G13*Supuestos!$C$16 -> -791 | H18: =-H13*Supuestos!$C$16 -> -980.84 | I18: =-I13*Supuestos!$C$16 -> -1233.96 | J18: =-J13*Supuestos!$C$16 -> -1550.36 | ... N18: =-N13*Supuestos!$C$16 -> -3765.16
B19: Mapas, ruteo y soporte | C19: =-C9*(Supuestos!$C$19+Supuestos!$C$20) -> -9000 | D19: =-D9*(Supuestos!$C$19+Supuestos!$C$20) -> -11700 | E19: =-E9*(Supuestos!$C$19+Supuestos!$C$20) -> -14400 | F19: =-F9*(Supuestos!$C$19+Supuestos!$C$20) -> -18000 | G19: =-G9*(Supuestos!$C$19+Supuestos!$C$20) -> -22500 | H19: =-H9*(Supuestos!$C$19+Supuestos!$C$20) -> -27900 | I19: =-I9*(Supuestos!$C$19+Supuestos!$C$20) -> -35100 | J19: =-J9*(Supuestos!$C$19+Supuestos!$C$20) -> -44100 | ... N19: =-N9*(Supuestos!$C$19+Supuestos!$C$20) -> -107100
B20: Margen de contribución | C20: =C15+SUM(C17:C19) -> 37541.6 | D20: =D15+SUM(D17:D19) -> 48804.08 | E20: =E15+SUM(E17:E19) -> 60066.56 | F20: =F15+SUM(F17:F19) -> 75083.2 | G20: =G15+SUM(G17:G19) -> 93854 | H20: =H15+SUM(H17:H19) -> 116378.96 | I20: =I15+SUM(I17:I19) -> 146412.24 | J20: =J15+SUM(J17:J19) -> 183953.84 | ... N20: =N15+SUM(N17:N19) -> 446745.04
B21: Costos fijos | C21: =-Supuestos!$C$42 -> -368000 | D21: =-Supuestos!$C$42 -> -368000 | E21: =-Supuestos!$C$42 -> -368000 | F21: =-Supuestos!$C$42 -> -368000 | G21: =-Supuestos!$C$42 -> -368000 | H21: =-Supuestos!$C$42 -> -368000 | I21: =-Supuestos!$C$42 -> -368000 | J21: =-Supuestos!$C$42 -> -368000 | ... N21: =-Supuestos!$C$42 -> -368000
B22: RESULTADO OPERATIVO (EBITDA) | C22: =C20+C21 -> -330458.4 | D22: =D20+D21 -> -319195.92 | E22: =E20+E21 -> -307933.44 | F22: =F20+F21 -> -292916.8 | G22: =G20+G21 -> -274146 | H22: =H20+H21 -> -251621.04 | I22: =I20+I21 -> -221587.76 | J22: =J20+J21 -> -184046.16 | ... N22: =N20+N21 -> 78745.04
B24: Take rate efectivo sobre GMV | C24: =IFERROR(C15/C10,0) -> 0.10394921 | D24: =IFERROR(D15/D10,0) -> 0.10394921 | E24: =IFERROR(E15/E10,0) -> 0.10394921 | F24: =IFERROR(F15/F10,0) -> 0.10394921 | G24: =IFERROR(G15/G10,0) -> 0.10394921 | H24: =IFERROR(H15/H10,0) -> 0.10394921 | I24: =IFERROR(I15/I10,0) -> 0.10394921 | J24: =IFERROR(J15/J10,0) -> 0.10394921 | ... N24: =IFERROR(N15/N10,0) -> 0.10394921
B25: Margen de contribución por conductor | C25: =IFERROR(C20/C5,0) -> 3754.16 | D25: =IFERROR(D20/D5,0) -> 3754.16 | E25: =IFERROR(E20/E5,0) -> 3754.16 | F25: =IFERROR(F20/F5,0) -> 3754.16 | G25: =IFERROR(G20/G5,0) -> 3754.16 | H25: =IFERROR(H20/H5,0) -> 3754.16 | I25: =IFERROR(I20/I5,0) -> 3754.16 | J25: =IFERROR(J20/J5,0) -> 3754.16 | ... N25: =IFERROR(N20/N5,0) -> 3754.16
B26: EBITDA en USD | C26: =C22/Supuestos!$C$5 -> -8261.46 | D26: =D22/Supuestos!$C$5 -> -7979.898 | E26: =E22/Supuestos!$C$5 -> -7698.336 | F26: =F22/Supuestos!$C$5 -> -7322.92 | G26: =G22/Supuestos!$C$5 -> -6853.65 | H26: =H22/Supuestos!$C$5 -> -6290.526 | I26: =I22/Supuestos!$C$5 -> -5539.694 | J26: =J22/Supuestos!$C$5 -> -4601.154 | ... N26: =N22/Supuestos!$C$5 -> 1968.626
B27: Nota: el mix de planes se mantiene constante, lo cual es optimista. En la práctica los conductores de
B28: alto volumen migran a Pro (selección adversa) y el take rate mezclado baja con el tiempo.

Sheet Sensibilidad
B1: Sensibilidad del plan Pro: precio × comisión
B2: Margen de contribución por conductor Pro, en UYU/mes. Rojo mental = negativo.
B3: Usa los viajes/mes, tarifa, % tarjeta y costos de la hoja Supuestos. Los ejes son editables (azul).
B5: Margen de contribución por conductor Pro (UYU/mes) | E5: Fuente / nota
B6: Comisión Pro ↓ / Cuota USD → | C6: 0 | D6: 20 | E6: 40 | F6: 55 | G6: 70 | H6: 85 | I6: 100 | J6: 130 | K6: 160
B7: 0 | C7: =(Supuestos!$C$9*Supuestos!$C$8*$B7)+(Supuestos!$C$9*Supuestos!$C$11)+(C$6*Supuestos!$C$5*(1-Supuestos!$C$16))-(Supuestos!$C$9*Supuestos!$C$8*Supuestos!$C$10*Supuestos!$C$14)-(Supuestos!$C$9*Supuestos!$C$10*Supuestos!$C$15)-(Supuestos!$C$9*(Supuestos!$C$19+Supuestos!$C$20)) -> -2763 | D7: =(Supuestos!$C$9*Supuestos!$C$8*$B7)+(Supuestos!$C$9*Supuestos!$C$11)+(D$6*Supuestos!$C$5*(1-Supuestos!$C$16))-(Supuestos!$C$9*Supuestos!$C$8*Supuestos!$C$10*Supuestos!$C$14)-(Supuestos!$C$9*Supuestos!$C$10*Supuestos!$C$15)-(Supuestos!$C$9*(Supuestos!$C$19+Supuestos!$C$20)) -> -1991 | E7: =(Supuestos!$C$9*Supuestos!$C$8*$B7)+(Supuestos!$C$9*Supuestos!$C$11)+(E$6*Supuestos!$C$5*(1-Supuestos!$C$16))-(Supuestos!$C$9*Supuestos!$C$8*Supuestos!$C$10*Supuestos!$C$14)-(Supuestos!$C$9*Supuestos!$C$10*Supuestos!$C$15)-(Supuestos!$C$9*(Supuestos!$C$19+Supuestos!$C$20)) -> -1219 | F7: =(Supuestos!$C$9*Supuestos!$C$8*$B7)+(Supuestos!$C$9*Supuestos!$C$11)+(F$6*Supuestos!$C$5*(1-Supuestos!$C$16))-(Supuestos!$C$9*Supuestos!$C$8*Supuestos!$C$10*Supuestos!$C$14)-(Supuestos!$C$9*Supuestos!$C$10*Supuestos!$C$15)-(Supuestos!$C$9*(Supuestos!$C$19+Supuestos!$C$20)) -> -640 | G7: =(Supuestos!$C$9*Supuestos!$C$8*$B7)+(Supuestos!$C$9*Supuestos!$C$11)+(G$6*Supuestos!$C$5*(1-Supuestos!$C$16))-(Supuestos!$C$9*Supuestos!$C$8*Supuestos!$C$10*Supuestos!$C$14)-(Supuestos!$C$9*Supuestos!$C$10*Supuestos!$C$15)-(Supuestos!$C$9*(Supuestos!$C$19+Supuestos!$C$20)) -> -61 | H7: =(Supuestos!$C$9*Supuestos!$C$8*$B7)+(Supuestos!$C$9*Supuestos!$C$11)+(H$6*Supuestos!$C$5*(1-Supuestos!$C$16))-(Supuestos!$C$9*Supuestos!$C$8*Supuestos!$C$10*Supuestos!$C$14)-(Supuestos!$C$9*Supuestos!$C$10*Supuestos!$C$15)-(Supuestos!$C$9*(Supuestos!$C$19+Supuestos!$C$20)) -> 518 | I7: =(Supuestos!$C$9*Supuestos!$C$8*$B7)+(Supuestos!$C$9*Supuestos!$C$11)+(I$6*Supuestos!$C$5*(1-Supuestos!$C$16))-(Supuestos!$C$9*Supuestos!$C$8*Supuestos!$C$10*Supuestos!$C$14)-(Supuestos!$C$9*Supuestos!$C$10*Supuestos!$C$15)-(Supuestos!$C$9*(Supuestos!$C$19+Supuestos!$C$20)) -> 1097 | J7: =(Supuestos!$C$9*Supuestos!$C$8*$B7)+(Supuestos!$C$9*Supuestos!$C$11)+(J$6*Supuestos!$C$5*(1-Supuestos!$C$16))-(Supuestos!$C$9*Supuestos!$C$8*Supuestos!$C$10*Supuestos!$C$14)-(Supuestos!$C$9*Supuestos!$C$10*Supuestos!$C$15)-(Supuestos!$C$9*(Supuestos!$C$19+Supuestos!$C$20)) -> 2255 | K7: =(Supuestos!$C$9*Supuestos!$C$8*$B7)+(Supuestos!$C$9*Supuestos!$C$11)+(K$6*Supuestos!$C$5*(1-Supuestos!$C$16))-(Supuestos!$C$9*Supuestos!$C$8*Supuestos!$C$10*Supuestos!$C$14)-(Supuestos!$C$9*Supuestos!$C$10*Supuestos!$C$15)-(Supuestos!$C$9*(Supuestos!$C$19+Supuestos!$C$20)) -> 3413
B8: 0.01 | C8: =(Supuestos!$C$9*Supuestos!$C$8*$B8)+(Supuestos!$C$9*Supuestos!$C$11)+(C$6*Supuestos!$C$5*(1-Supuestos!$C$16))-(Supuestos!$C$9*Supuestos!$C$8*Supuestos!$C$10*Supuestos!$C$14)-(Supuestos!$C$9*Supuestos!$C$10*Supuestos!$C$15)-(Supuestos!$C$9*(Supuestos!$C$19+Supuestos!$C$20)) -> -2133 | D8: =(Supuestos!$C$9*Supuestos!$C$8*$B8)+(Supuestos!$C$9*Supuestos!$C$11)+(D$6*Supuestos!$C$5*(1-Supuestos!$C$16))-(Supuestos!$C$9*Supuestos!$C$8*Supuestos!$C$10*Supuestos!$C$14)-(Supuestos!$C$9*Supuestos!$C$10*Supuestos!$C$15)-(Supuestos!$C$9*(Supuestos!$C$19+Supuestos!$C$20)) -> -1361 | E8: =(Supuestos!$C$9*Supuestos!$C$8*$B8)+(Supuestos!$C$9*Supuestos!$C$11)+(E$6*Supuestos!$C$5*(1-Supuestos!$C$16))-(Supuestos!$C$9*Supuestos!$C$8*Supuestos!$C$10*Supuestos!$C$14)-(Supuestos!$C$9*Supuestos!$C$10*Supuestos!$C$15)-(Supuestos!$C$9*(Supuestos!$C$19+Supuestos!$C$20)) -> -589 | F8: =(Supuestos!$C$9*Supuestos!$C$8*$B8)+(Supuestos!$C$9*Supuestos!$C$11)+(F$6*Supuestos!$C$5*(1-Supuestos!$C$16))-(Supuestos!$C$9*Supuestos!$C$8*Supuestos!$C$10*Supuestos!$C$14)-(Supuestos!$C$9*Supuestos!$C$10*Supuestos!$C$15)-(Supuestos!$C$9*(Supuestos!$C$19+Supuestos!$C$20)) -> -10 | G8: =(Supuestos!$C$9*Supuestos!$C$8*$B8)+(Supuestos!$C$9*Supuestos!$C$11)+(G$6*Supuestos!$C$5*(1-Supuestos!$C$16))-(Supuestos!$C$9*Supuestos!$C$8*Supuestos!$C$10*Supuestos!$C$14)-(Supuestos!$C$9*Supuestos!$C$10*Supuestos!$C$15)-(Supuestos!$C$9*(Supuestos!$C$19+Supuestos!$C$20)) -> 569 | H8: =(Supuestos!$C$9*Supuestos!$C$8*$B8)+(Supuestos!$C$9*Supuestos!$C$11)+(H$6*Supuestos!$C$5*(1-Supuestos!$C$16))-(Supuestos!$C$9*Supuestos!$C$8*Supuestos!$C$10*Supuestos!$C$14)-(Supuestos!$C$9*Supuestos!$C$10*Supuestos!$C$15)-(Supuestos!$C$9*(Supuestos!$C$19+Supuestos!$C$20)) -> 1148 | I8: =(Supuestos!$C$9*Supuestos!$C$8*$B8)+(Supuestos!$C$9*Supuestos!$C$11)+(I$6*Supuestos!$C$5*(1-Supuestos!$C$16))-(Supuestos!$C$9*Supuestos!$C$8*Supuestos!$C$10*Supuestos!$C$14)-(Supuestos!$C$9*Supuestos!$C$10*Supuestos!$C$15)-(Supuestos!$C$9*(Supuestos!$C$19+Supuestos!$C$20)) -> 1727 | J8: =(Supuestos!$C$9*Supuestos!$C$8*$B8)+(Supuestos!$C$9*Supuestos!$C$11)+(J$6*Supuestos!$C$5*(1-Supuestos!$C$16))-(Supuestos!$C$9*Supuestos!$C$8*Supuestos!$C$10*Supuestos!$C$14)-(Supuestos!$C$9*Supuestos!$C$10*Supuestos!$C$15)-(Supuestos!$C$9*(Supuestos!$C$19+Supuestos!$C$20)) -> 2885 | K8: =(Supuestos!$C$9*Supuestos!$C$8*$B8)+(Supuestos!$C$9*Supuestos!$C$11)+(K$6*Supuestos!$C$5*(1-Supuestos!$C$16))-(Supuestos!$C$9*Supuestos!$C$8*Supuestos!$C$10*Supuestos!$C$14)-(Supuestos!$C$9*Supuestos!$C$10*Supuestos!$C$15)-(Supuestos!$C$9*(Supuestos!$C$19+Supuestos!$C$20)) -> 4043
B9: 0.02 | C9: =(Supuestos!$C$9*Supuestos!$C$8*$B9)+(Supuestos!$C$9*Supuestos!$C$11)+(C$6*Supuestos!$C$5*(1-Supuestos!$C$16))-(Supuestos!$C$9*Supuestos!$C$8*Supuestos!$C$10*Supuestos!$C$14)-(Supuestos!$C$9*Supuestos!$C$10*Supuestos!$C$15)-(Supuestos!$C$9*(Supuestos!$C$19+Supuestos!$C$20)) -> -1503 | D9: =(Supuestos!$C$9*Supuestos!$C$8*$B9)+(Supuestos!$C$9*Supuestos!$C$11)+(D$6*Supuestos!$C$5*(1-Supuestos!$C$16))-(Supuestos!$C$9*Supuestos!$C$8*Supuestos!$C$10*Supuestos!$C$14)-(Supuestos!$C$9*Supuestos!$C$10*Supuestos!$C$15)-(Supuestos!$C$9*(Supuestos!$C$19+Supuestos!$C$20)) -> -731 | E9: =(Supuestos!$C$9*Supuestos!$C$8*$B9)+(Supuestos!$C$9*Supuestos!$C$11)+(E$6*Supuestos!$C$5*(1-Supuestos!$C$16))-(Supuestos!$C$9*Supuestos!$C$8*Supuestos!$C$10*Supuestos!$C$14)-(Supuestos!$C$9*Supuestos!$C$10*Supuestos!$C$15)-(Supuestos!$C$9*(Supuestos!$C$19+Supuestos!$C$20)) -> 41 | F9: =(Supuestos!$C$9*Supuestos!$C$8*$B9)+(Supuestos!$C$9*Supuestos!$C$11)+(F$6*Supuestos!$C$5*(1-Supuestos!$C$16))-(Supuestos!$C$9*Supuestos!$C$8*Supuestos!$C$10*Supuestos!$C$14)-(Supuestos!$C$9*Supuestos!$C$10*Supuestos!$C$15)-(Supuestos!$C$9*(Supuestos!$C$19+Supuestos!$C$20)) -> 620 | G9: =(Supuestos!$C$9*Supuestos!$C$8*$B9)+(Supuestos!$C$9*Supuestos!$C$11)+(G$6*Supuestos!$C$5*(1-Supuestos!$C$16))-(Supuestos!$C$9*Supuestos!$C$8*Supuestos!$C$10*Supuestos!$C$14)-(Supuestos!$C$9*Supuestos!$C$10*Supuestos!$C$15)-(Supuestos!$C$9*(Supuestos!$C$19+Supuestos!$C$20)) -> 1199 | H9: =(Supuestos!$C$9*Supuestos!$C$8*$B9)+(Supuestos!$C$9*Supuestos!$C$11)+(H$6*Supuestos!$C$5*(1-Supuestos!$C$16))-(Supuestos!$C$9*Supuestos!$C$8*Supuestos!$C$10*Supuestos!$C$14)-(Supuestos!$C$9*Supuestos!$C$10*Supuestos!$C$15)-(Supuestos!$C$9*(Supuestos!$C$19+Supuestos!$C$20)) -> 1778 | I9: =(Supuestos!$C$9*Supuestos!$C$8*$B9)+(Supuestos!$C$9*Supuestos!$C$11)+(I$6*Supuestos!$C$5*(1-Supuestos!$C$16))-(Supuestos!$C$9*Supuestos!$C$8*Supuestos!$C$10*Supuestos!$C$14)-(Supuestos!$C$9*Supuestos!$C$10*Supuestos!$C$15)-(Supuestos!$C$9*(Supuestos!$C$19+Supuestos!$C$20)) -> 2357 | J9: =(Supuestos!$C$9*Supuestos!$C$8*$B9)+(Supuestos!$C$9*Supuestos!$C$11)+(J$6*Supuestos!$C$5*(1-Supuestos!$C$16))-(Supuestos!$C$9*Supuestos!$C$8*Supuestos!$C$10*Supuestos!$C$14)-(Supuestos!$C$9*Supuestos!$C$10*Supuestos!$C$15)-(Supuestos!$C$9*(Supuestos!$C$19+Supuestos!$C$20)) -> 3515 | K9: =(Supuestos!$C$9*Supuestos!$C$8*$B9)+(Supuestos!$C$9*Supuestos!$C$11)+(K$6*Supuestos!$C$5*(1-Supuestos!$C$16))-(Supuestos!$C$9*Supuestos!$C$8*Supuestos!$C$10*Supuestos!$C$14)-(Supuestos!$C$9*Supuestos!$C$10*Supuestos!$C$15)-(Supuestos!$C$9*(Supuestos!$C$19+Supuestos!$C$20)) -> 4673
B10: 0.03 | C10: =(Supuestos!$C$9*Supuestos!$C$8*$B10)+(Supuestos!$C$9*Supuestos!$C$11)+(C$6*Supuestos!$C$5*(1-Supuestos!$C$16))-(Supuestos!$C$9*Supuestos!$C$8*Supuestos!$C$10*Supuestos!$C$14)-(Supuestos!$C$9*Supuestos!$C$10*Supuestos!$C$15)-(Supuestos!$C$9*(Supuestos!$C$19+Supuestos!$C$20)) -> -873 | D10: =(Supuestos!$C$9*Supuestos!$C$8*$B10)+(Supuestos!$C$9*Supuestos!$C$11)+(D$6*Supuestos!$C$5*(1-Supuestos!$C$16))-(Supuestos!$C$9*Supuestos!$C$8*Supuestos!$C$10*Supuestos!$C$14)-(Supuestos!$C$9*Supuestos!$C$10*Supuestos!$C$15)-(Supuestos!$C$9*(Supuestos!$C$19+Supuestos!$C$20)) -> -101 | E10: =(Supuestos!$C$9*Supuestos!$C$8*$B10)+(Supuestos!$C$9*Supuestos!$C$11)+(E$6*Supuestos!$C$5*(1-Supuestos!$C$16))-(Supuestos!$C$9*Supuestos!$C$8*Supuestos!$C$10*Supuestos!$C$14)-(Supuestos!$C$9*Supuestos!$C$10*Supuestos!$C$15)-(Supuestos!$C$9*(Supuestos!$C$19+Supuestos!$C$20)) -> 671 | F10: =(Supuestos!$C$9*Supuestos!$C$8*$B10)+(Supuestos!$C$9*Supuestos!$C$11)+(F$6*Supuestos!$C$5*(1-Supuestos!$C$16))-(Supuestos!$C$9*Supuestos!$C$8*Supuestos!$C$10*Supuestos!$C$14)-(Supuestos!$C$9*Supuestos!$C$10*Supuestos!$C$15)-(Supuestos!$C$9*(Supuestos!$C$19+Supuestos!$C$20)) -> 1250 | G10: =(Supuestos!$C$9*Supuestos!$C$8*$B10)+(Supuestos!$C$9*Supuestos!$C$11)+(G$6*Supuestos!$C$5*(1-Supuestos!$C$16))-(Supuestos!$C$9*Supuestos!$C$8*Supuestos!$C$10*Supuestos!$C$14)-(Supuestos!$C$9*Supuestos!$C$10*Supuestos!$C$15)-(Supuestos!$C$9*(Supuestos!$C$19+Supuestos!$C$20)) -> 1829 | H10: =(Supuestos!$C$9*Supuestos!$C$8*$B10)+(Supuestos!$C$9*Supuestos!$C$11)+(H$6*Supuestos!$C$5*(1-Supuestos!$C$16))-(Supuestos!$C$9*Supuestos!$C$8*Supuestos!$C$10*Supuestos!$C$14)-(Supuestos!$C$9*Supuestos!$C$10*Supuestos!$C$15)-(Supuestos!$C$9*(Supuestos!$C$19+Supuestos!$C$20)) -> 2408 | I10: =(Supuestos!$C$9*Supuestos!$C$8*$B10)+(Supuestos!$C$9*Supuestos!$C$11)+(I$6*Supuestos!$C$5*(1-Supuestos!$C$16))-(Supuestos!$C$9*Supuestos!$C$8*Supuestos!$C$10*Supuestos!$C$14)-(Supuestos!$C$9*Supuestos!$C$10*Supuestos!$C$15)-(Supuestos!$C$9*(Supuestos!$C$19+Supuestos!$C$20)) -> 2987 | J10: =(Supuestos!$C$9*Supuestos!$C$8*$B10)+(Supuestos!$C$9*Supuestos!$C$11)+(J$6*Supuestos!$C$5*(1-Supuestos!$C$16))-(Supuestos!$C$9*Supuestos!$C$8*Supuestos!$C$10*Supuestos!$C$14)-(Supuestos!$C$9*Supuestos!$C$10*Supuestos!$C$15)-(Supuestos!$C$9*(Supuestos!$C$19+Supuestos!$C$20)) -> 4145 | K10: =(Supuestos!$C$9*Supuestos!$C$8*$B10)+(Supuestos!$C$9*Supuestos!$C$11)+(K$6*Supuestos!$C$5*(1-Supuestos!$C$16))-(Supuestos!$C$9*Supuestos!$C$8*Supuestos!$C$10*Supuestos!$C$14)-(Supuestos!$C$9*Supuestos!$C$10*Supuestos!$C$15)-(Supuestos!$C$9*(Supuestos!$C$19+Supuestos!$C$20)) -> 5303
B11: 0.05 | C11: =(Supuestos!$C$9*Supuestos!$C$8*$B11)+(Supuestos!$C$9*Supuestos!$C$11)+(C$6*Supuestos!$C$5*(1-Supuestos!$C$16))-(Supuestos!$C$9*Supuestos!$C$8*Supuestos!$C$10*Supuestos!$C$14)-(Supuestos!$C$9*Supuestos!$C$10*Supuestos!$C$15)-(Supuestos!$C$9*(Supuestos!$C$19+Supuestos!$C$20)) -> 387 | D11: =(Supuestos!$C$9*Supuestos!$C$8*$B11)+(Supuestos!$C$9*Supuestos!$C$11)+(D$6*Supuestos!$C$5*(1-Supuestos!$C$16))-(Supuestos!$C$9*Supuestos!$C$8*Supuestos!$C$10*Supuestos!$C$14)-(Supuestos!$C$9*Supuestos!$C$10*Supuestos!$C$15)-(Supuestos!$C$9*(Supuestos!$C$19+Supuestos!$C$20)) -> 1159 | E11: =(Supuestos!$C$9*Supuestos!$C$8*$B11)+(Supuestos!$C$9*Supuestos!$C$11)+(E$6*Supuestos!$C$5*(1-Supuestos!$C$16))-(Supuestos!$C$9*Supuestos!$C$8*Supuestos!$C$10*Supuestos!$C$14)-(Supuestos!$C$9*Supuestos!$C$10*Supuestos!$C$15)-(Supuestos!$C$9*(Supuestos!$C$19+Supuestos!$C$20)) -> 1931 | F11: =(Supuestos!$C$9*Supuestos!$C$8*$B11)+(Supuestos!$C$9*Supuestos!$C$11)+(F$6*Supuestos!$C$5*(1-Supuestos!$C$16))-(Supuestos!$C$9*Supuestos!$C$8*Supuestos!$C$10*Supuestos!$C$14)-(Supuestos!$C$9*Supuestos!$C$10*Supuestos!$C$15)-(Supuestos!$C$9*(Supuestos!$C$19+Supuestos!$C$20)) -> 2510 | G11: =(Supuestos!$C$9*Supuestos!$C$8*$B11)+(Supuestos!$C$9*Supuestos!$C$11)+(G$6*Supuestos!$C$5*(1-Supuestos!$C$16))-(Supuestos!$C$9*Supuestos!$C$8*Supuestos!$C$10*Supuestos!$C$14)-(Supuestos!$C$9*Supuestos!$C$10*Supuestos!$C$15)-(Supuestos!$C$9*(Supuestos!$C$19+Supuestos!$C$20)) -> 3089 | H11: =(Supuestos!$C$9*Supuestos!$C$8*$B11)+(Supuestos!$C$9*Supuestos!$C$11)+(H$6*Supuestos!$C$5*(1-Supuestos!$C$16))-(Supuestos!$C$9*Supuestos!$C$8*Supuestos!$C$10*Supuestos!$C$14)-(Supuestos!$C$9*Supuestos!$C$10*Supuestos!$C$15)-(Supuestos!$C$9*(Supuestos!$C$19+Supuestos!$C$20)) -> 3668 | I11: =(Supuestos!$C$9*Supuestos!$C$8*$B11)+(Supuestos!$C$9*Supuestos!$C$11)+(I$6*Supuestos!$C$5*(1-Supuestos!$C$16))-(Supuestos!$C$9*Supuestos!$C$8*Supuestos!$C$10*Supuestos!$C$14)-(Supuestos!$C$9*Supuestos!$C$10*Supuestos!$C$15)-(Supuestos!$C$9*(Supuestos!$C$19+Supuestos!$C$20)) -> 4247 | J11: =(Supuestos!$C$9*Supuestos!$C$8*$B11)+(Supuestos!$C$9*Supuestos!$C$11)+(J$6*Supuestos!$C$5*(1-Supuestos!$C$16))-(Supuestos!$C$9*Supuestos!$C$8*Supuestos!$C$10*Supuestos!$C$14)-(Supuestos!$C$9*Supuestos!$C$10*Supuestos!$C$15)-(Supuestos!$C$9*(Supuestos!$C$19+Supuestos!$C$20)) -> 5405 | K11: =(Supuestos!$C$9*Supuestos!$C$8*$B11)+(Supuestos!$C$9*Supuestos!$C$11)+(K$6*Supuestos!$C$5*(1-Supuestos!$C$16))-(Supuestos!$C$9*Supuestos!$C$8*Supuestos!$C$10*Supuestos!$C$14)-(Supuestos!$C$9*Supuestos!$C$10*Supuestos!$C$15)-(Supuestos!$C$9*(Supuestos!$C$19+Supuestos!$C$20)) -> 6563
B12: 0.07 | C12: =(Supuestos!$C$9*Supuestos!$C$8*$B12)+(Supuestos!$C$9*Supuestos!$C$11)+(C$6*Supuestos!$C$5*(1-Supuestos!$C$16))-(Supuestos!$C$9*Supuestos!$C$8*Supuestos!$C$10*Supuestos!$C$14)-(Supuestos!$C$9*Supuestos!$C$10*Supuestos!$C$15)-(Supuestos!$C$9*(Supuestos!$C$19+Supuestos!$C$20)) -> 1647 | D12: =(Supuestos!$C$9*Supuestos!$C$8*$B12)+(Supuestos!$C$9*Supuestos!$C$11)+(D$6*Supuestos!$C$5*(1-Supuestos!$C$16))-(Supuestos!$C$9*Supuestos!$C$8*Supuestos!$C$10*Supuestos!$C$14)-(Supuestos!$C$9*Supuestos!$C$10*Supuestos!$C$15)-(Supuestos!$C$9*(Supuestos!$C$19+Supuestos!$C$20)) -> 2419 | E12: =(Supuestos!$C$9*Supuestos!$C$8*$B12)+(Supuestos!$C$9*Supuestos!$C$11)+(E$6*Supuestos!$C$5*(1-Supuestos!$C$16))-(Supuestos!$C$9*Supuestos!$C$8*Supuestos!$C$10*Supuestos!$C$14)-(Supuestos!$C$9*Supuestos!$C$10*Supuestos!$C$15)-(Supuestos!$C$9*(Supuestos!$C$19+Supuestos!$C$20)) -> 3191 | F12: =(Supuestos!$C$9*Supuestos!$C$8*$B12)+(Supuestos!$C$9*Supuestos!$C$11)+(F$6*Supuestos!$C$5*(1-Supuestos!$C$16))-(Supuestos!$C$9*Supuestos!$C$8*Supuestos!$C$10*Supuestos!$C$14)-(Supuestos!$C$9*Supuestos!$C$10*Supuestos!$C$15)-(Supuestos!$C$9*(Supuestos!$C$19+Supuestos!$C$20)) -> 3770 | G12: =(Supuestos!$C$9*Supuestos!$C$8*$B12)+(Supuestos!$C$9*Supuestos!$C$11)+(G$6*Supuestos!$C$5*(1-Supuestos!$C$16))-(Supuestos!$C$9*Supuestos!$C$8*Supuestos!$C$10*Supuestos!$C$14)-(Supuestos!$C$9*Supuestos!$C$10*Supuestos!$C$15)-(Supuestos!$C$9*(Supuestos!$C$19+Supuestos!$C$20)) -> 4349 | H12: =(Supuestos!$C$9*Supuestos!$C$8*$B12)+(Supuestos!$C$9*Supuestos!$C$11)+(H$6*Supuestos!$C$5*(1-Supuestos!$C$16))-(Supuestos!$C$9*Supuestos!$C$8*Supuestos!$C$10*Supuestos!$C$14)-(Supuestos!$C$9*Supuestos!$C$10*Supuestos!$C$15)-(Supuestos!$C$9*(Supuestos!$C$19+Supuestos!$C$20)) -> 4928 | I12: =(Supuestos!$C$9*Supuestos!$C$8*$B12)+(Supuestos!$C$9*Supuestos!$C$11)+(I$6*Supuestos!$C$5*(1-Supuestos!$C$16))-(Supuestos!$C$9*Supuestos!$C$8*Supuestos!$C$10*Supuestos!$C$14)-(Supuestos!$C$9*Supuestos!$C$10*Supuestos!$C$15)-(Supuestos!$C$9*(Supuestos!$C$19+Supuestos!$C$20)) -> 5507 | J12: =(Supuestos!$C$9*Supuestos!$C$8*$B12)+(Supuestos!$C$9*Supuestos!$C$11)+(J$6*Supuestos!$C$5*(1-Supuestos!$C$16))-(Supuestos!$C$9*Supuestos!$C$8*Supuestos!$C$10*Supuestos!$C$14)-(Supuestos!$C$9*Supuestos!$C$10*Supuestos!$C$15)-(Supuestos!$C$9*(Supuestos!$C$19+Supuestos!$C$20)) -> 6665 | K12: =(Supuestos!$C$9*Supuestos!$C$8*$B12)+(Supuestos!$C$9*Supuestos!$C$11)+(K$6*Supuestos!$C$5*(1-Supuestos!$C$16))-(Supuestos!$C$9*Supuestos!$C$8*Supuestos!$C$10*Supuestos!$C$14)-(Supuestos!$C$9*Supuestos!$C$10*Supuestos!$C$15)-(Supuestos!$C$9*(Supuestos!$C$19+Supuestos!$C$20)) -> 7823
B13: 0.09 | C13: =(Supuestos!$C$9*Supuestos!$C$8*$B13)+(Supuestos!$C$9*Supuestos!$C$11)+(C$6*Supuestos!$C$5*(1-Supuestos!$C$16))-(Supuestos!$C$9*Supuestos!$C$8*Supuestos!$C$10*Supuestos!$C$14)-(Supuestos!$C$9*Supuestos!$C$10*Supuestos!$C$15)-(Supuestos!$C$9*(Supuestos!$C$19+Supuestos!$C$20)) -> 2907 | D13: =(Supuestos!$C$9*Supuestos!$C$8*$B13)+(Supuestos!$C$9*Supuestos!$C$11)+(D$6*Supuestos!$C$5*(1-Supuestos!$C$16))-(Supuestos!$C$9*Supuestos!$C$8*Supuestos!$C$10*Supuestos!$C$14)-(Supuestos!$C$9*Supuestos!$C$10*Supuestos!$C$15)-(Supuestos!$C$9*(Supuestos!$C$19+Supuestos!$C$20)) -> 3679 | E13: =(Supuestos!$C$9*Supuestos!$C$8*$B13)+(Supuestos!$C$9*Supuestos!$C$11)+(E$6*Supuestos!$C$5*(1-Supuestos!$C$16))-(Supuestos!$C$9*Supuestos!$C$8*Supuestos!$C$10*Supuestos!$C$14)-(Supuestos!$C$9*Supuestos!$C$10*Supuestos!$C$15)-(Supuestos!$C$9*(Supuestos!$C$19+Supuestos!$C$20)) -> 4451 | F13: =(Supuestos!$C$9*Supuestos!$C$8*$B13)+(Supuestos!$C$9*Supuestos!$C$11)+(F$6*Supuestos!$C$5*(1-Supuestos!$C$16))-(Supuestos!$C$9*Supuestos!$C$8*Supuestos!$C$10*Supuestos!$C$14)-(Supuestos!$C$9*Supuestos!$C$10*Supuestos!$C$15)-(Supuestos!$C$9*(Supuestos!$C$19+Supuestos!$C$20)) -> 5030 | G13: =(Supuestos!$C$9*Supuestos!$C$8*$B13)+(Supuestos!$C$9*Supuestos!$C$11)+(G$6*Supuestos!$C$5*(1-Supuestos!$C$16))-(Supuestos!$C$9*Supuestos!$C$8*Supuestos!$C$10*Supuestos!$C$14)-(Supuestos!$C$9*Supuestos!$C$10*Supuestos!$C$15)-(Supuestos!$C$9*(Supuestos!$C$19+Supuestos!$C$20)) -> 5609 | H13: =(Supuestos!$C$9*Supuestos!$C$8*$B13)+(Supuestos!$C$9*Supuestos!$C$11)+(H$6*Supuestos!$C$5*(1-Supuestos!$C$16))-(Supuestos!$C$9*Supuestos!$C$8*Supuestos!$C$10*Supuestos!$C$14)-(Supuestos!$C$9*Supuestos!$C$10*Supuestos!$C$15)-(Supuestos!$C$9*(Supuestos!$C$19+Supuestos!$C$20)) -> 6188 | I13: =(Supuestos!$C$9*Supuestos!$C$8*$B13)+(Supuestos!$C$9*Supuestos!$C$11)+(I$6*Supuestos!$C$5*(1-Supuestos!$C$16))-(Supuestos!$C$9*Supuestos!$C$8*Supuestos!$C$10*Supuestos!$C$14)-(Supuestos!$C$9*Supuestos!$C$10*Supuestos!$C$15)-(Supuestos!$C$9*(Supuestos!$C$19+Supuestos!$C$20)) -> 6767 | J13: =(Supuestos!$C$9*Supuestos!$C$8*$B13)+(Supuestos!$C$9*Supuestos!$C$11)+(J$6*Supuestos!$C$5*(1-Supuestos!$C$16))-(Supuestos!$C$9*Supuestos!$C$8*Supuestos!$C$10*Supuestos!$C$14)-(Supuestos!$C$9*Supuestos!$C$10*Supuestos!$C$15)-(Supuestos!$C$9*(Supuestos!$C$19+Supuestos!$C$20)) -> 7925 | K13: =(Supuestos!$C$9*Supuestos!$C$8*$B13)+(Supuestos!$C$9*Supuestos!$C$11)+(K$6*Supuestos!$C$5*(1-Supuestos!$C$16))-(Supuestos!$C$9*Supuestos!$C$8*Supuestos!$C$10*Supuestos!$C$14)-(Supuestos!$C$9*Supuestos!$C$10*Supuestos!$C$15)-(Supuestos!$C$9*(Supuestos!$C$19+Supuestos!$C$20)) -> 9083
B14: 0.12 | C14: =(Supuestos!$C$9*Supuestos!$C$8*$B14)+(Supuestos!$C$9*Supuestos!$C$11)+(C$6*Supuestos!$C$5*(1-Supuestos!$C$16))-(Supuestos!$C$9*Supuestos!$C$8*Supuestos!$C$10*Supuestos!$C$14)-(Supuestos!$C$9*Supuestos!$C$10*Supuestos!$C$15)-(Supuestos!$C$9*(Supuestos!$C$19+Supuestos!$C$20)) -> 4797 | D14: =(Supuestos!$C$9*Supuestos!$C$8*$B14)+(Supuestos!$C$9*Supuestos!$C$11)+(D$6*Supuestos!$C$5*(1-Supuestos!$C$16))-(Supuestos!$C$9*Supuestos!$C$8*Supuestos!$C$10*Supuestos!$C$14)-(Supuestos!$C$9*Supuestos!$C$10*Supuestos!$C$15)-(Supuestos!$C$9*(Supuestos!$C$19+Supuestos!$C$20)) -> 5569 | E14: =(Supuestos!$C$9*Supuestos!$C$8*$B14)+(Supuestos!$C$9*Supuestos!$C$11)+(E$6*Supuestos!$C$5*(1-Supuestos!$C$16))-(Supuestos!$C$9*Supuestos!$C$8*Supuestos!$C$10*Supuestos!$C$14)-(Supuestos!$C$9*Supuestos!$C$10*Supuestos!$C$15)-(Supuestos!$C$9*(Supuestos!$C$19+Supuestos!$C$20)) -> 6341 | F14: =(Supuestos!$C$9*Supuestos!$C$8*$B14)+(Supuestos!$C$9*Supuestos!$C$11)+(F$6*Supuestos!$C$5*(1-Supuestos!$C$16))-(Supuestos!$C$9*Supuestos!$C$8*Supuestos!$C$10*Supuestos!$C$14)-(Supuestos!$C$9*Supuestos!$C$10*Supuestos!$C$15)-(Supuestos!$C$9*(Supuestos!$C$19+Supuestos!$C$20)) -> 6920 | G14: =(Supuestos!$C$9*Supuestos!$C$8*$B14)+(Supuestos!$C$9*Supuestos!$C$11)+(G$6*Supuestos!$C$5*(1-Supuestos!$C$16))-(Supuestos!$C$9*Supuestos!$C$8*Supuestos!$C$10*Supuestos!$C$14)-(Supuestos!$C$9*Supuestos!$C$10*Supuestos!$C$15)-(Supuestos!$C$9*(Supuestos!$C$19+Supuestos!$C$20)) -> 7499 | H14: =(Supuestos!$C$9*Supuestos!$C$8*$B14)+(Supuestos!$C$9*Supuestos!$C$11)+(H$6*Supuestos!$C$5*(1-Supuestos!$C$16))-(Supuestos!$C$9*Supuestos!$C$8*Supuestos!$C$10*Supuestos!$C$14)-(Supuestos!$C$9*Supuestos!$C$10*Supuestos!$C$15)-(Supuestos!$C$9*(Supuestos!$C$19+Supuestos!$C$20)) -> 8078 | I14: =(Supuestos!$C$9*Supuestos!$C$8*$B14)+(Supuestos!$C$9*Supuestos!$C$11)+(I$6*Supuestos!$C$5*(1-Supuestos!$C$16))-(Supuestos!$C$9*Supuestos!$C$8*Supuestos!$C$10*Supuestos!$C$14)-(Supuestos!$C$9*Supuestos!$C$10*Supuestos!$C$15)-(Supuestos!$C$9*(Supuestos!$C$19+Supuestos!$C$20)) -> 8657 | J14: =(Supuestos!$C$9*Supuestos!$C$8*$B14)+(Supuestos!$C$9*Supuestos!$C$11)+(J$6*Supuestos!$C$5*(1-Supuestos!$C$16))-(Supuestos!$C$9*Supuestos!$C$8*Supuestos!$C$10*Supuestos!$C$14)-(Supuestos!$C$9*Supuestos!$C$10*Supuestos!$C$15)-(Supuestos!$C$9*(Supuestos!$C$19+Supuestos!$C$20)) -> 9815 | K14: =(Supuestos!$C$9*Supuestos!$C$8*$B14)+(Supuestos!$C$9*Supuestos!$C$11)+(K$6*Supuestos!$C$5*(1-Supuestos!$C$16))-(Supuestos!$C$9*Supuestos!$C$8*Supuestos!$C$10*Supuestos!$C$14)-(Supuestos!$C$9*Supuestos!$C$10*Supuestos!$C$15)-(Supuestos!$C$9*(Supuestos!$C$19+Supuestos!$C$20)) -> 10973
B15: 0.15 | C15: =(Supuestos!$C$9*Supuestos!$C$8*$B15)+(Supuestos!$C$9*Supuestos!$C$11)+(C$6*Supuestos!$C$5*(1-Supuestos!$C$16))-(Supuestos!$C$9*Supuestos!$C$8*Supuestos!$C$10*Supuestos!$C$14)-(Supuestos!$C$9*Supuestos!$C$10*Supuestos!$C$15)-(Supuestos!$C$9*(Supuestos!$C$19+Supuestos!$C$20)) -> 6687 | D15: =(Supuestos!$C$9*Supuestos!$C$8*$B15)+(Supuestos!$C$9*Supuestos!$C$11)+(D$6*Supuestos!$C$5*(1-Supuestos!$C$16))-(Supuestos!$C$9*Supuestos!$C$8*Supuestos!$C$10*Supuestos!$C$14)-(Supuestos!$C$9*Supuestos!$C$10*Supuestos!$C$15)-(Supuestos!$C$9*(Supuestos!$C$19+Supuestos!$C$20)) -> 7459 | E15: =(Supuestos!$C$9*Supuestos!$C$8*$B15)+(Supuestos!$C$9*Supuestos!$C$11)+(E$6*Supuestos!$C$5*(1-Supuestos!$C$16))-(Supuestos!$C$9*Supuestos!$C$8*Supuestos!$C$10*Supuestos!$C$14)-(Supuestos!$C$9*Supuestos!$C$10*Supuestos!$C$15)-(Supuestos!$C$9*(Supuestos!$C$19+Supuestos!$C$20)) -> 8231 | F15: =(Supuestos!$C$9*Supuestos!$C$8*$B15)+(Supuestos!$C$9*Supuestos!$C$11)+(F$6*Supuestos!$C$5*(1-Supuestos!$C$16))-(Supuestos!$C$9*Supuestos!$C$8*Supuestos!$C$10*Supuestos!$C$14)-(Supuestos!$C$9*Supuestos!$C$10*Supuestos!$C$15)-(Supuestos!$C$9*(Supuestos!$C$19+Supuestos!$C$20)) -> 8810 | G15: =(Supuestos!$C$9*Supuestos!$C$8*$B15)+(Supuestos!$C$9*Supuestos!$C$11)+(G$6*Supuestos!$C$5*(1-Supuestos!$C$16))-(Supuestos!$C$9*Supuestos!$C$8*Supuestos!$C$10*Supuestos!$C$14)-(Supuestos!$C$9*Supuestos!$C$10*Supuestos!$C$15)-(Supuestos!$C$9*(Supuestos!$C$19+Supuestos!$C$20)) -> 9389 | H15: =(Supuestos!$C$9*Supuestos!$C$8*$B15)+(Supuestos!$C$9*Supuestos!$C$11)+(H$6*Supuestos!$C$5*(1-Supuestos!$C$16))-(Supuestos!$C$9*Supuestos!$C$8*Supuestos!$C$10*Supuestos!$C$14)-(Supuestos!$C$9*Supuestos!$C$10*Supuestos!$C$15)-(Supuestos!$C$9*(Supuestos!$C$19+Supuestos!$C$20)) -> 9968 | I15: =(Supuestos!$C$9*Supuestos!$C$8*$B15)+(Supuestos!$C$9*Supuestos!$C$11)+(I$6*Supuestos!$C$5*(1-Supuestos!$C$16))-(Supuestos!$C$9*Supuestos!$C$8*Supuestos!$C$10*Supuestos!$C$14)-(Supuestos!$C$9*Supuestos!$C$10*Supuestos!$C$15)-(Supuestos!$C$9*(Supuestos!$C$19+Supuestos!$C$20)) -> 10547 | J15: =(Supuestos!$C$9*Supuestos!$C$8*$B15)+(Supuestos!$C$9*Supuestos!$C$11)+(J$6*Supuestos!$C$5*(1-Supuestos!$C$16))-(Supuestos!$C$9*Supuestos!$C$8*Supuestos!$C$10*Supuestos!$C$14)-(Supuestos!$C$9*Supuestos!$C$10*Supuestos!$C$15)-(Supuestos!$C$9*(Supuestos!$C$19+Supuestos!$C$20)) -> 11705 | K15: =(Supuestos!$C$9*Supuestos!$C$8*$B15)+(Supuestos!$C$9*Supuestos!$C$11)+(K$6*Supuestos!$C$5*(1-Supuestos!$C$16))-(Supuestos!$C$9*Supuestos!$C$8*Supuestos!$C$10*Supuestos!$C$14)-(Supuestos!$C$9*Supuestos!$C$10*Supuestos!$C$15)-(Supuestos!$C$9*(Supuestos!$C$19+Supuestos!$C$20)) -> 12863
B17: Referencias
B18: Tu propuesta actual (US$ 70 / 2%) | C18: =G9 -> 1199 | E18: Fila de 2%, columna de US$ 70.
B19: Comisión mínima — viaje PROMEDIO (mix de pagos) | C19: =IFERROR((Supuestos!C10*Supuestos!C14*Supuestos!C8+Supuestos!C10*Supuestos!C15+Supuestos!C19+Supuestos!C20-Supuestos!C11)/Supuestos!C8,"n/a") -> 0.043857143 | E19: Pondera el procesamiento por el % de viajes con tarjeta. Es el umbral del P&L mensual.
B20: Margen de un conductor Free (referencia) | C20: =Unit_Economics!C21 -> 4797 | E20: Para comparar contra las celdas de arriba.
B21: Comisión mínima — viaje pagado CON TARJETA | C21: =IFERROR((Supuestos!C14*Supuestos!C8+Supuestos!C15+Supuestos!C19+Supuestos!C20-Supuestos!C11)/Supuestos!C8,"n/a") -> 0.063571429 | E21: Umbral estricto: ese viaje carga el 100% del costo de procesar. Si el conductor puede cobrar todo con tarjeta, este es el número que manda.
B23: Cómo leer esta grilla
B24: · Buscá la primera columna donde tu fila de comisión deja de ser negativa: esa es la cuota mínima viable.
B25: · Bajá por la columna de US$ 70 y fijate a qué comisión el margen se vuelve cómodo: esa es la comisión que deberías cobrar.
B26: · Poné un fee de servicio de 20-30 UYU en Supuestos!C11 y volvé acá. La grilla entera se corre para arriba.
B27: · Un margen positivo acá NO alcanza: todavía tiene que cubrir los costos fijos de la hoja PL_Plataforma.
